[
  { "id":"e1-1", "tab":"elementary", "grade":"小学1年生", "subject":"国語", "color":"rose", "title":"ひらがな・カタカナ", "tags":["1年","文字","基本","導入"], "pdfBasic":"#", "pdfAdv":"#", "pdfAns":"#" },
  { "id":"e1-2", "tab":"elementary", "grade":"小学1年生", "subject":"算数", "color":"sky", "title":"かずとたしざん", "tags":["1年","計算","足し算","基本"], "pdfBasic":"#", "pdfAdv":"#", "pdfAns":"#" },
  { "id":"e2-1", "tab":"elementary", "grade":"小学2年生", "subject":"国語", "color":"rose", "title":"かん字の練習", "tags":["2年","漢字","書写"], "pdfBasic":"#", "pdfAdv":"#", "pdfAns":"#" },
  { "id":"e2-2", "tab":"elementary", "grade":"小学2年生", "subject":"算数", "color":"sky", "title":"かけ算(九九)", "tags":["2年","九九","計算","重要"], "pdfBasic":"#", "pdfAdv":"#", "pdfAns":"#" },
  { "id":"e3-1", "tab":"elementary", "grade":"小学3年生", "subject":"算数", "color":"sky", "title":"わり算と分数", "tags":["3年","割り算","分数","計算"], "pdfBasic":"#", "pdfAdv":"#", "pdfAns":"#" },
  { "id":"e3-2", "tab":"elementary", "grade":"小学3年生", "subject":"理科", "color":"emerald", "title":"昆虫の育ち方", "tags":["3年","虫","生き物","観察"], "pdfBasic":"#", "pdfAdv":"#", "pdfAns":"#" },
  { "id":"e6-2", "tab":"elementary", "grade":"小学6年生", "subject":"社会", "color":"amber", "title":"日本の歴史", "tags":["6年","武士","歴史","江戸"], "pdfBasic":"#", "pdfAdv":"#", "pdfAns":"#" },
  { "id":"j1-1", "tab":"junior", "grade":"中学1年生", "subject":"数学", "color":"sky", "title":"正負の数・方程式", "tags":["中1","数学","計算"], "pdfBasic":"#", "pdfAdv":"#", "pdfAns":"#" },
  { "id":"j3-2", "tab":"junior", "grade":"中学3年生", "subject":"英語", "color":"violet", "title":"現在完了・関係代名詞", "tags":["中3","文法","重要"], "pdfBasic":"#", "pdfAdv":"#", "pdfAns":"#" }
]
